ioavstatsdb/__init__.py
ioavstatsdb/__init__.pyi
ioavstatsdb/avstats.py
ioavstatsdb/avstats.pyi
ioavstatsdb/code_generator.py
ioavstatsdb/code_generator.pyi
ioavstatsdb/db_ddl_base.py
ioavstatsdb/db_dml_base.py
ioavstatsdb/db_dml_corr.py
ioavstatsdb/db_utils.py
ioavstatsdb/db_utils.pyi
ioavstatsdb/io_config.py
ioavstatsdb/io_glob.py
ioavstatsdb/io_glob.pyi
ioavstatsdb/io_utils.py
ioavstatsdb/io_utils.pyi
ioavstatsdb/py.typed
ioavstatsdb-1.5.0a99.dist-info/LICENSE.md
ioavstatsdb-1.5.0a99.dist-info/METADATA
ioavstatsdb-1.5.0a99.dist-info/WHEEL
ioavstatsdb-1.5.0a99.dist-info/top_level.txt
ioavstatsdb-1.5.0a99.dist-info/RECORD
