Metadata-Version: 2.1
Name: ioavstatsdb
Version: 1.5.0a99
Summary: Aviation Event Statistics - Database Software
Author-email: Team IO-Aero <info@io-aero.com>
Maintainer-email: Team IO-Aero <info@io-aero.ch>
Project-URL: Bug Tracker, https://github.com/io-aero/io-avstats-db/issues
Project-URL: Documentation, https://io-aero.github.io/io-avstats-db/
Project-URL: Homepage, https://github.com/io-aero/io-avstats-db
Project-URL: Release History, https://io-aero.github.io/io-avstats-db/release_history/
Project-URL: Release Notes, https://io-aero.github.io/io-avstats-db/release_notes/
Project-URL: Source, https://github.com/io-aero/io-avstats-db/ioavstatsdb/
Keywords: Accidents,Aviation,NTSB,Statistics
Classifier: Development Status :: 5 - Production/Stable
Classifier: Environment :: Console
Classifier: Intended Audience :: Science/Research
Classifier: License :: Other/Proprietary License
Classifier: Programming Language :: Python :: 3.10
Classifier: Topic :: Scientific/Engineering
Classifier: Typing :: Typed
Requires-Python: >=3.10
License-File: LICENSE.md
